rvsfunc/NNEDI3.py
rvsfunc/__init__.py
rvsfunc/dvd.py
rvsfunc/edgecase.py
rvsfunc/errors.py
rvsfunc/masking.py
rvsfunc/utils.py
rvsfunc-0.1.2.1.dist-info/LICENSE
rvsfunc-0.1.2.1.dist-info/METADATA
rvsfunc-0.1.2.1.dist-info/WHEEL
rvsfunc-0.1.2.1.dist-info/top_level.txt
rvsfunc-0.1.2.1.dist-info/RECORD
