Metadata-Version: 2.1
Name: rvsfunc
Version: 0.1.2.1
Summary: VapourSynth functions written or modified by Riven Skaye
Home-page: https://github.com/RivenSkaye/rvsfunc
Author: Riven Skaye
Author-email: riven@tae.moe
Project-URL: Bug Tracker, https://github.com/RivenSkaye/rvsfunc/issues
Project-URL: Docs, https://rvsfunc.tae.moe/
Classifier: Programming Language :: Python :: 3
Classifier: Programming Language :: Python :: 3 :: Only
Classifier: License :: OSI Approved :: MIT License
Classifier: Operating System :: OS Independent
Classifier: Development Status :: 4 - Beta
Classifier: Natural Language :: English
Classifier: Topic :: Multimedia :: Graphics
Requires-Python: >=3.8
License-File: LICENSE
Requires-Dist: VapourSynth (>=51)
Requires-Dist: vsutil (>=0.5.0)
Requires-Dist: numpy (>=1.21.1)
